dwml/__init__.py
dwml/latex_dict.py
dwml/omml.py
dwml/utils.py
dwml-0.3.dist-info/LICENSE
dwml-0.3.dist-info/METADATA
dwml-0.3.dist-info/WHEEL
dwml-0.3.dist-info/top_level.txt
dwml-0.3.dist-info/RECORD
