Metadata-Version: 2.1
Name: dwml
Version: 0.3
Summary: ms-office omml to latex converter
Home-page: UNKNOWN
Author: xilei
Author-email: xilei125@163.com
License: http://www.apache.org/licenses/LICENSE-2.0
Keywords: word,excel,omml,latex
Platform: UNKNOWN
Classifier: Development Status :: 4 - Beta
Classifier: Programming Language :: Python :: 2.7
Classifier: Programming Language :: Python :: 3
Classifier: Programming Language :: Python :: 3.3
Classifier: Programming Language :: Python :: 3.4
Classifier: Programming Language :: Python :: Implementation :: CPython
Classifier: Programming Language :: Python :: Implementation :: PyPy
